dekprompt-0.1.5.dist-info/METADATA
dekprompt-0.1.5.dist-info/WHEEL
dekprompt-0.1.5.dist-info/entry_points.txt
dekprompt/__init__.py
dekprompt/cfg/__init__.py
dekprompt/func.py
dekprompt/prompt.py
dekprompt/unit.py
dekprompt/utils/__init__.py
dekprompt-0.1.5.dist-info/RECORD
